dask_ml/__init__.py
dask_ml/_compat.py
dask_ml/_partial.py
dask_ml/_typing.py
dask_ml/_utils.py
dask_ml/base.py
dask_ml/datasets.py
dask_ml/impute.py
dask_ml/naive_bayes.py
dask_ml/neural_network.py
dask_ml/utils.py
dask_ml/wrappers.py
dask_ml/xgboost.py
dask_ml/cluster/__init__.py
dask_ml/cluster/_compat.py
dask_ml/cluster/k_means.py
dask_ml/cluster/spectral.py
dask_ml/compose/__init__.py
dask_ml/compose/_column_transformer.py
dask_ml/decomposition/__init__.py
dask_ml/decomposition/_compat.py
dask_ml/decomposition/extmath.py
dask_ml/decomposition/incremental_pca.py
dask_ml/decomposition/pca.py
dask_ml/decomposition/truncated_svd.py
dask_ml/ensemble/__init__.py
dask_ml/ensemble/_blockwise.py
dask_ml/feature_extraction/__init__.py
dask_ml/feature_extraction/text.py
dask_ml/linear_model/__init__.py
dask_ml/linear_model/glm.py
dask_ml/linear_model/perceptron.py
dask_ml/linear_model/utils.py
dask_ml/metrics/__init__.py
dask_ml/metrics/classification.py
dask_ml/metrics/pairwise.py
dask_ml/metrics/regression.py
dask_ml/metrics/scorer.py
dask_ml/model_selection/__init__.py
dask_ml/model_selection/_hyperband.py
dask_ml/model_selection/_incremental.py
dask_ml/model_selection/_normalize.py
dask_ml/model_selection/_search.py
dask_ml/model_selection/_split.py
dask_ml/model_selection/_successive_halving.py
dask_ml/model_selection/methods.py
dask_ml/model_selection/utils.py
dask_ml/model_selection/utils_test.py
dask_ml/preprocessing/__init__.py
dask_ml/preprocessing/_block_transformer.py
dask_ml/preprocessing/_encoders.py
dask_ml/preprocessing/data.py
dask_ml/preprocessing/label.py
dask_ml-2024.3.20.dist-info/LICENSE.txt
dask_ml-2024.3.20.dist-info/METADATA
dask_ml-2024.3.20.dist-info/WHEEL
dask_ml-2024.3.20.dist-info/top_level.txt
dask_ml-2024.3.20.dist-info/RECORD
